{
    "950": "Hitman Blood Money Trailer",
    "95000": "Super Splatters",
    "95300": "Capsized",
    "95400": "ibb & obb",
    "95700": "The Cat and the Coup",
    "95900": "Air Conflicts Secret Wars",
    "950050": "Starlink Battle for Atlas",
    "950100": "PRO EVOLUTION SOCCER 2019 LITE",
    "950130": "Evidence of Life",
    "950140": "Hiding Spot",
    "950160": "Miracle Circus",
    "950180": "Lemnis Gate",
    "950210": "SUFFER",
    "950230": "Elephant Rave 2",
    "950240": "Rise of the Pirates",
    "950250": "Halfway Home",
    "950260": "Divenia",
    "950300": "REDO!",
    "950310": "Glo Phlox",
    "950330": "OIL PATCH SIMULATIONS",
    "950360": "Quest room Hanon",
    "950370": "Tactics & Strategy Master 2Princess of Holy Light（圣光战姬）",
    "950380": "Hang Up",
    "950460": "Paradise Cleaning!",
    "950490": "INFILTRIA",
    "950530": "Mojo 2 Mia",
    "950560": "HITMAN™ 2 - Whittleton Creek",
    "950570": "Bitworm",
    "950590": "Epic Roller Coasters — Dread Blood",
    "950600": "Zoological Era",
    "950620": "Priest Simulator Vampire Show",
    "950670": "Gothic Playable Teaser",
    "950700": "VICCP",
    "950730": "Fallen Sky -Online-",
    "950740": "China Mao's legacy",
    "950750": "Dega Madness",
    "950760": "Ostalgie Legacy of Hoxha",
    "950810": "SquareWorld Unpixeled",
    "950820": "Hiveswap Friendsim - Volume Thirteen",
    "950830": "The Pusher",
    "950850": "The Window Box",
    "950860": "Spiral Clicker",
    "950890": "Game Master Plus",
    "950910": "Space Bugs",
    "950990": "Business Magnate",
    "951000": "Trap Shrine",
    "951010": "Zero spring episode 1 English translation version",
    "951030": "Derelict (DO NOT BUY)",
    "951050": "Another Hardcore Game",
    "951100": "The Adventures of Team Australia",
    "951110": "VR Cricket",
    "951130": "心之檻",
    "951160": "JUMP UP",
    "951190": "Ancient lands the Tsar awakening",
    "951220": "Pumpkin Death Garden",
    "951240": "Obenseuer",
    "951250": "Not Heaven",
    "951260": "Shieldwall Chronicles Swords of the North",
    "951330": "Weaponry Dealer VR",
    "951360": "Super Potato Bruh",
    "951370": "Drawkanoid",
    "951420": "Refraction",
    "951430": "Dead Age 2 The Zombie Survival RPG",
    "951440": "Volcanoids",
    "951450": "Fit It",
    "951460": "Circle Empires Apex Monsters!",
    "951470": "Unrest Indigo",
    "951490": "Stream Battlecards",
    "951530": "Alien Shooter - Last Hope",
    "951570": "Deadness",
    "951610": "Another Sight - Hodge Skins",
    "951620": "Bygone Dreams",
    "951640": "Gangsta Sniper",
    "951660": "Steep - X-Games Pass",
    "951670": "Precipice",
    "951680": "Dream Home",
    "951690": "Surge",
    "951700": "Super Jigsaw Puzzle Space",
    "951740": "Nice Shot! The Gun Golfing Game",
    "951750": "I Am Dead",
    "951760": "Full Body Workout",
    "951770": "Forsaken Realms Vahrin's Call",
    "951800": "Softspace",
    "951820": "Captain Bones  A Pirate's Journey",
    "951830": "The Last Sovereign",
    "951860": "Once Ever After",
    "951870": "Indie Pogo Prisonbreak Zorbie Skin",
    "951930": "Typing Incremental",
    "951940": "Almost There The Platformer",
    "951990": "Pepper's Castle",
    "952000": "Be Vigilant!",
    "952010": "The Martian Job",
    "952020": "Love at Elevation",
    "952040": "MUSYNX",
    "952050": "Buddinpals",
    "952060": "Resident Evil 3",
    "952080": "DRAGON BALL FighterZ – Anime Music Pack 2",
    "952090": "Grand Strategy",
    "952100": "Bad Pixels",
    "952120": "阿达三国志2019  竖版 Three Kingdoms 2019",
    "952130": "Origin of Decay",
    "952140": "Surrogate",
    "952150": "NORN9",
    "952170": "Master Car Creation in Blender",
    "952200": "stikir",
    "952230": "5 Star Miami Resort",
    "952240": "Dieselpunk Wars",
    "952250": "SEPTEMBER 1999",
    "952290": "Zueirama",
    "952330": "Blackfoot Burrows",
    "952370": "Armored Fighter",
    "952390": "World of Warships — 10 Guineas",
    "952400": "Oculto",
    "952420": "Shan Gui II Sweet Osmanthus II",
    "952460": "Lovecraft Quest - A Comix Game",
    "952490": "Hello Charlotte Heaven's Gate",
    "952510": "Chronicles of Lurra",
    "952540": "Romancing SaGa 3™",
    "952600": "Fireflies",
    "952640": "Ride the Thunder A Vietnam War Story of Victory & Betrayal",
    "952650": "My Magical Demon Lover - Cheat Map",
    "952680": "Blind Girl",
    "952700": "DEAD",
    "952860": "河洛群俠傳 (Ho Tu Lo Shu ： The Books of Dragon)",
    "952890": "Surviving Mars Green Planet",
    "952900": "Tomoyo After - CLANNADTomoyo After Piano Arrange Album \"Piano no Mori\"",
    "952910": "Lantern of Worlds - The First Quest",
    "952920": "Hoyeonjigi",
    "952930": "ArmZ VR",
    "952950": "03.04",
    "952960": "Hentai IQ Puzzle - Puzzle Pack 5 IQ",
    "952970": "Stick to the end",
    "953020": "DRAGON BALL XENOVERSE 2 - Anime Music Pack 2",
    "953060": "Go to IT",
    "953080": "Tangledeep - Legend of Shara",
    "953120": "ADK",
    "953140": "Hegis' Grasp - Boss Rush Expansion",
    "953150": "TrivaTune",
    "953170": "Witch's Tales",
    "953190": "Dream Walker",
    "953220": "Corrupted Commander",
    "953230": "Quiver Dick's Terrible Tale For Terrible Parents To Read To Their Equally Terrible Children",
    "953240": "Spicy Deck",
    "953250": "War Machines Free to Play",
    "953270": "Dominatrix Simulator Threshold",
    "953280": "Emirati Tales",
    "953290": "Dinosaur Safari VR",
    "953300": "ART SQOOL",
    "953330": "Hyper Echelon",
    "953340": "Colourless",
    "953370": "ZED",
    "953440": "And You're There, Too",
    "953490": "CARRION",
    "953550": "Temple Scramble",
    "953570": "White Dove 白雀",
    "953580": "Tourist Bus Simulator",
    "953610": "HOT GIRLS VR",
    "953640": "Gyro Buster",
    "953680": "Tourist Bus Simulator - Comfort Class HD",
    "953690": "Doom & Destiny Worlds",
    "953700": "I'm an adventurer",
    "953800": "Zaccaria Pinball - Nautilus 2018 Table",
    "953830": "天命奇御 Fate Seeker - 伏虎迷蹤",
    "953840": "Apollo 11 VR HD",
    "953870": "Space Robinson Hardcore Roguelike Action",
    "953880": "First Class Trouble",
    "953900": "Pantsu Hunter Back to the 90s",
    "953910": "Wars Across The World Innsmouth 1928",
    "953920": "Palace of the Azure Dragon",
    "953940": "Jurassic World Evolution Secrets of Dr Wu",
    "953950": "Kubble",
    "953980": "Shadows Awakening - The Chromaton Chronicles",
    "953990": "Heart of the Kingdom Rebellion",
    "954000": "Cosa Nostra",
    "954010": "Definitely Sneaky But Not Sneaky",
    "954060": "West of Loathing Reckonin' at Gun Manor",
    "954070": "Beat Boxers",
    "954080": "Memorrha",
    "954150": "Nowhere Girl",
    "954160": "Angelus Brand VR Experience",
    "954170": "Backyard Brawl",
    "954210": "Symphonic Mayhem",
    "954240": "Cuboid Keeper",
    "954270": "LOGistICAL 2",
    "954280": "3dSen VR",
    "954300": "6 Keys The Gym",
    "954350": "NOLO HOME",
    "954360": "Color by Numbers - Halloween",
    "954400": "Color by Numbers - Christmas",
    "954410": "Color by Numbers - Animals",
    "954420": "DotX",
    "954530": "The Momo Game",
    "954560": "Light Bearers Full Game",
    "954590": "TEXT",
    "954600": "Groove Coaster - Battle Against a True Hero",
    "954610": "Onii-chan Asobo",
    "954650": "Druidstone The Secret of the Menhir Forest",
    "954690": "Not Tonight (Original Soundtrack)",
    "954720": "The Shedding",
    "954740": "Terminator Resistance",
    "954760": "The Cells",
    "954780": "Zombie Soldier",
    "954860": "Mad Cat's World. Act - 1 Not by meat alone...",
    "954870": "Astrox Imperium",
    "954880": "PanoPainter",
    "954920": "Flank That Tank!",
    "954940": "Merchant - Boost Potion Recipes",
    "954950": "Merchant - Additional Inventory Page",
    "954970": "Golden Key",
    "955010": "ARCHWIZARD",
    "955030": "Metamorph",
    "955050": "Bright Memory",
    "955070": "Forex Trading Master Simulator",
    "955120": "SCUOS",
    "955170": "铁道物语：陆王（Railway SagaLand King）",
    "955180": "Shan Gui II Episode 2",
    "955190": "Blueprint Word Classroom",
    "955200": "Spurdo D",
    "955210": "Hentai Shooter 3D Uncensored Edition",
    "955250": "Weirdest Thing",
    "955260": "Island Invasion",
    "955300": "ShotKill",
    "955320": "Dark Fantasy Jigsaw Puzzle",
    "955360": "Stronghold A Hero's Fate",
    "955370": "Weyrwood",
    "955400": "Bonds",
    "955410": "Armoured Alliance",
    "955470": "The Royal Game of Ur",
    "955490": "Terror In The Atomic Desert",
    "955500": "MagnetoBotty",
    "955530": "Wildest of the Wild",
    "955540": "Telecube Nightmare",
    "955550": "Root Beer On Tap",
    "955560": "Evenicle",
    "955570": "Teck Boxing 3D",
    "955580": "Rise Race The Future",
    "955590": "HARDCORE MECHA - Round Hammer Particle Cannon",
    "955600": "Noble In Exile  落魄之家",
    "955610": "OpenVR Benchmark",
    "955640": "Go Outside Simulator",
    "955650": "Dreams of the Dying (Enderal Novels, Book I)",
    "955670": "Acropolis The Archaic Age",
    "955700": "TITAN HUNTER",
    "955740": "Mini Healer",
    "955780": "Enderal The Bard Songs",
    "955830": "Hentai Shooter 3D - Uncensored Art Collection",
    "955840": "Slide to finish",
    "955860": "Woodboy",
    "955870": "Battlecruisers",
    "955900": "Amazing Cultivation Simulator",
    "955980": "Dive Inside",
    "956000": "Su Hack",
    "956010": "Hexanome",
    "956030": "Creaks",
    "956060": "Mittelborg City of Mages",
    "956070": "Graviteam Tactics Chewy Gooey Pass",
    "956090": "Animals Memory Horses",
    "956140": "Lifeslide",
    "956190": "Cat's Puzzle  ᐠ｡ꞈ｡ᐟ",
    "956200": "Leopoldo Manquiseil",
    "956210": "Spec Defense",
    "956240": "Simson Tuningwerkstatt 3D",
    "956280": "Joe's Wrath",
    "956310": "Musashi vs Cthulhu",
    "956350": "There Is No Turning Back!",
    "956360": "Badminton Warrior (羽毛球勇士 中国新年版)",
    "956380": "Dark Dimensions Homecoming Collector's Edition",
    "956390": "Final Cut Fame Fatale Collector's Edition",
    "956400": "Grim Tales Bloody Mary Collector's Edition",
    "956430": "Steampunk Graveyard",
    "956450": "Rogue Fable III",
    "956490": "Lucy Got Problems - 18+ Adult Only Patch",
    "956500": "Bow to Blood Last Captain Standing",
    "956540": "Color Phase",
    "956550": "Devil Girl Needs Massages",
    "956560": "StarCrossed",
    "956580": "9Dragons  Kung Fu Arena",
    "956590": "Yet Another Snake Game",
    "956600": "Magebuster Amorous Augury",
    "956620": "Talk to Yuno",
    "956640": "Bless Online Warlord Pack - Official Launch Edition",
    "956650": "Bless Online Legendary Warlord Pack - Official Launch Edition",
    "956680": "M.A.S.S. Builder",
    "956700": "Xiahou Dun - Officer Ticket  夏侯惇使用券",
    "956720": "Zhao Yun - Officer Ticket  趙雲使用券",
    "956730": "Zhang He - Officer Ticket  張郃使用券",
    "956750": "Ma Chao - Officer Ticket  馬超使用券",
    "956760": "Pang Tong - Officer Ticket  龐統使用券",
    "956770": "Jiang Wei - Officer Ticket  姜維使用券",
    "956860": "Sima Zhao - Officer Ticket  司馬昭使用券",
    "956870": "Starship Zvezda",
    "956880": "Géants disparus VR",
    "956890": "Lianshi - Officer Ticket  練師使用券",
    "956900": "Loca-Love Theme Song EP",
    "956920": "Yue Jin - Officer Ticket  楽進使用券",
    "956930": "Zhang Bao - Officer Ticket  張苞使用券",
    "956940": "Guan Yinping - Officer Ticket  関銀屏使用券",
    "956990": "Slavistan 2",
    "957070": "iB Cricket",
    "957080": "EEP 15",
    "957110": "DCS MiG-29 Flaming Cliffs",
    "957140": "新世勇者传 Newera Heroes' Chronicle",
    "957150": "冷月清辉照天涯(KUNG FU LEGEND)",
    "957220": "Our Worst Fears",
    "957280": "COUCH VERSUS",
    "957350": "Rogue Rails",
    "957410": "King of Queendoms",
    "957430": "Mentai Uncensored",
    "957440": "Swords and Sandals Pirates",
    "957490": "My Cabin And I",
    "957510": "The Hour Has Come",
    "957570": "The Qaedon Wars - The Story Begins",
    "957630": "Demonheart - Dev's Coffee",
    "957660": "Catizens",
    "957680": "Doughlings Invasion",
    "957690": "HITMAN™ 2 - Expansion Pass",
    "957720": "Strategic Command WWII World at War",
    "957770": "WarpThrough",
    "957780": "Tower of Fate",
    "957790": "War Dust VR 32v32 Battlefields",
    "957810": "Season of War (Beta)",
    "957820": "Across the Grooves",
    "957830": "Crystal Maidens",
    "957840": "Furious Road",
    "957850": "Light Up the Holidays",
    "957880": "League Of Superheros",
    "957890": "The Horologist's Legacy",
    "957900": "Jigsaw Puzzle Pack - Pixel Puzzles Ultimate Variety Pack 11",
    "957910": "Jigsaw Puzzle Pack - Pixel Puzzles Ultimate Ukiyo-e 2",
    "957930": "Intelligence Underwater Kingdom",
    "957950": "1971 Indian Naval Front",
    "957960": "Inkulinati",
    "958050": "1001st Hyper Tower",
    "958070": "Jurassic Shark",
    "958090": "School of the Dead Anastasia",
    "958110": "尸毒来袭 - Zombie Virus Attack",
    "958130": "NEET simulator",
    "958190": "Surge Radio",
    "958200": "Ralf",
    "958210": "Pixelmash",
    "958260": "DEAD OR ALIVE Xtreme Venus Vacation",
    "958280": "Float Night",
    "958300": "Cute Girls 可爱的女孩",
    "958310": "Evolo.SpiderSim",
    "958320": "A Front Too Far Normandy",
    "958360": "Silver Child",
    "958370": "Monster Prom Second Term",
    "958380": "Wildlife Park 3 - Africa",
    "958480": "Seed of the Dead",
    "958490": "Titan shield",
    "958510": "Assault on Hyperion Base",
    "958520": "33 Immortals",
    "958530": "Fury of Dracula Digital Edition",
    "958590": "Pussy Riot The Movement",
    "958600": "BnB Wallpapers and Savefile",
    "958640": "Super Turbo Sudoku",
    "958650": "Strange Encounter",
    "958670": "MekaFighters",
    "958680": "Self-knowledge VR",
    "958690": "The Sky Climber",
    "958710": "RIFT - 7-day FREE Patron Pass",
    "958720": "Second Chance",
    "958740": "Heretic Operative",
    "958750": "Re-O-Ri",
    "958760": "Mary Loss of Soul",
    "958790": "Big Breezy Boat - Relaxing Sailing",
    "958850": "Let It Flow",
    "958880": "Nick Bounty and the Dame with the Blue Chewed Shoe",
    "958930": "Ricky Recharge",
    "958950": "GRIP Combat Racing - Official Artbook and Game Manual",
    "958980": "Pang and Bang",
    "959000": "Edna & Harvey The Breakout - Anniversary Edition",
    "959020": "You Shall Not Break!",
    "959030": "Zombie Cubes",
    "959050": "Bound Up & Squirming!",
    "959060": "RideOp - New Heights Expansion pack",
    "959080": "Unsung Warriors - Prologue",
    "959090": "WayDown",
    "959130": "Dandy & Randy",
    "959150": "Making History The First World War",
    "959160": "Hiveswap Friendsim - Volume Fourteen",
    "959170": "JohnCondemned",
    "959200": "Battleships and Carriers - WW2 Battleship Game",
    "959240": "Boom",
    "959280": "Total Seclusion",
    "959340": "Deconstruction Lab",
    "959350": "Sengoku Neet",
    "959400": "Save Thine Kingdom",
    "959410": "The Endless Empty",
    "959500": "Cute Puzzle",
    "959510": "The Master Club",
    "959520": "Fantasy Blacksmith",
    "959540": "Devil's Toy",
    "959590": "Super Keepy Ups",
    "959710": "the earth is a better person than me",
    "959730": "Spider Lander",
    "959750": "A Book of Beasts and Buddies",
    "959760": "Play Room 0g",
    "959770": "Moe The Boundary of Reality",
    "959800": "TIRELESS Prepare For The Adrenaline",
    "959820": "DragonFangZ - Extra Dungeon \"The Inferno Hollow\"",
    "959860": "The Valiant",
    "959870": "The Monster",
    "959880": "Dungeon Town",
    "959890": "Sister Travel",
    "959920": "VR Curling",
    "959930": "Duality"
}